[
  {
    "id": 58574416,
    "name": "Wild West Sarsaparilla"
  },
  {
    "id": 410001793,
    "name": "Rainbow Hot Air Balloon"
  },
  {
    "id": 72069888,
    "name": "Heartbreaker"
  },
  {
    "id": 96095042,
    "name": "Sorcus&#x27; Chair"
  },
  {
    "id": 146047188,
    "name": "Presidential Vampire Slaying Ax"
  },
  {
    "id": 2470984833,
    "name": "Pumpkin Trick or Treat Pail"
  },
  {
    "id": 124126871,
    "name": "Newtrat&#x27;s Tuskinator"
  },
  {
    "id": 163995329,
    "name": "Epic Duck Roped"
  },
  {
    "id": 139577901,
    "name": "Festive Periastron Chi"
  },
  {
    "id": 467138029,
    "name": "Robot Dance Gun"
  },
  {
    "id": 71037076,
    "name": "Arabian Knight Scimitar"
  },
  {
    "id": 32353654,
    "name": "Moonwalk Dance Potion"
  },
  {
    "id": 170903216,
    "name": "Pizza Delivery Vehicle"
  },
  {
    "id": 114020538,
    "name": "Astral Cloak of Transportation"
  },
  {
    "id": 95354259,
    "name": "Forbidden Box"
  },
  {
    "id": 81154592,
    "name": "Firebrand"
  },
  {
    "id": 97756645,
    "name": "Merely&#x27;s ROBLOX Tablet"
  },
  {
    "id": 341110180,
    "name": "Rainbow Omega Katana"
  },
  {
    "id": 124126528,
    "name": "Seranok&#x27;s Golden Chalice of Fame"
  },
  {
    "id": 37821008,
    "name": "ROBLOX Best Buy Card"
  }
]