[
  {
    "id": 16435306,
    "name": "Protest: More Gear Nao"
  },
  {
    "id": 304720496,
    "name": "Zombie Crossbow"
  },
  {
    "id": 18446266,
    "name": "Pilgrim Bear"
  },
  {
    "id": 156467963,
    "name": "Redcliff Ballista"
  },
  {
    "id": 182273893,
    "name": "Trick or Treat Sack"
  },
  {
    "id": 54130543,
    "name": "Sword Fish"
  },
  {
    "id": 101854660,
    "name": "2013 Firework"
  },
  {
    "id": 16201421,
    "name": "Reset Tool"
  },
  {
    "id": 93722515,
    "name": "Halloween Transmuter"
  },
  {
    "id": 149222485,
    "name": "My Big Fat Zombie Goldfish: The Seaquel"
  },
  {
    "id": 738924664,
    "name": "Carrot Slingshot"
  },
  {
    "id": 2620523875,
    "name": "Moose Mount "
  },
  {
    "id": 183665514,
    "name": "Axe of Blinding Justice"
  },
  {
    "id": 85145680,
    "name": "Pararocket"
  },
  {
    "id": 515688182,
    "name": "Nerf Zombie Potion"
  },
  {
    "id": 178076831,
    "name": "Redcliff Crossbow"
  },
  {
    "id": 94233367,
    "name": "Ghost Blaster"
  },
  {
    "id": 253485047,
    "name": "Galactic Hot Dogs"
  },
  {
    "id": 92142829,
    "name": "Rayvenge Sword"
  },
  {
    "id": 16200402,
    "name": "Clone Part"
  }
]